prog_test_445/__init__.py
prog_test_445/func.py
prog_test_445-0.1.0.dist-info/METADATA
prog_test_445-0.1.0.dist-info/WHEEL
prog_test_445-0.1.0.dist-info/RECORD
