Metadata-Version: 2.1
Name: prog-test-445
Version: 0.1.0
Summary: 
Author: Александр Смирнов
Author-email: alexsmi4444@gmail.com
Requires-Python: >=3.11,<4.0
Classifier: Programming Language :: Python :: 3
Classifier: Programming Language :: Python :: 3.11
Requires-Dist: requests (>=2.31.0,<3.0.0)
